[
    {
        "Date": "12/1/2020",
        "Open": "29797.50",
        "High": "30637.47",
        "Low": "29599.29",
        "Close": "30606.48"
    },
    {
        "Date": "11/1/2020",
        "Open": "26691.28",
        "High": "30116.51",
        "Low": "26691.28",
        "Close": "29638.64"
    },
    {
        "Date": "10/1/2020",
        "Open": "27940.63",
        "High": "28957.90",
        "Low": "26143.77",
        "Close": "26501.60"
    },
    {
        "Date": "9/1/2020",
        "Open": "28439.61",
        "High": "29199.35",
        "Low": "26537.01",
        "Close": "27781.70"
    },
    {
        "Date": "8/1/2020",
        "Open": "26542.32",
        "High": "28733.35",
        "Low": "26534.38",
        "Close": "28430.05"
    },
    {
        "Date": "7/1/2020",
        "Open": "25879.38",
        "High": "27071.33",
        "Low": "25523.51",
        "Close": "26428.32"
    },
    {
        "Date": "6/1/2020",
        "Open": "25342.99",
        "High": "27580.21",
        "Low": "24843.18",
        "Close": "25812.88"
    },
    {
        "Date": "5/1/2020",
        "Open": "24120.78",
        "High": "25758.79",
        "Low": "22789.62",
        "Close": "25383.11"
    },
    {
        "Date": "4/1/2020",
        "Open": "21227.38",
        "High": "24764.77",
        "Low": "20735.02",
        "Close": "24345.72"
    },
    {
        "Date": "3/1/2020",
        "Open": "25590.51",
        "High": "27102.34",
        "Low": "18213.65",
        "Close": "21917.16"
    },
    {
        "Date": "2/1/2020",
        "Open": "28319.65",
        "High": "29568.57",
        "Low": "24681.01",
        "Close": "25409.36"
    },
    {
        "Date": "1/1/2020",
        "Open": "28638.97",
        "High": "29373.62",
        "Low": "28169.53",
        "Close": "28256.03"
    },
    {
        "Date": "12/1/2019",
        "Open": "28109.74",
        "High": "28701.66",
        "Low": "27325.13",
        "Close": "28538.44"
    },
    {
        "Date": "11/1/2019",
        "Open": "27142.95",
        "High": "28174.97",
        "Low": "27142.95",
        "Close": "28051.41"
    },
    {
        "Date": "10/1/2019",
        "Open": "26962.54",
        "High": "27204.36",
        "Low": "25743.46",
        "Close": "27046.23"
    },
    {
        "Date": "9/1/2019",
        "Open": "26198.26",
        "High": "27306.73",
        "Low": "25978.22",
        "Close": "26916.83"
    },
    {
        "Date": "8/1/2019",
        "Open": "26879.86",
        "High": "27175.59",
        "Low": "25339.60",
        "Close": "26403.28"
    },
    {
        "Date": "7/1/2019",
        "Open": "26805.86",
        "High": "27398.68",
        "Low": "26616.21",
        "Close": "26864.27"
    },
    {
        "Date": "6/1/2019",
        "Open": "24830.16",
        "High": "26907.37",
        "Low": "24680.57",
        "Close": "26599.96"
    },
    {
        "Date": "5/1/2019",
        "Open": "26639.06",
        "High": "26689.39",
        "Low": "24809.51",
        "Close": "24815.04"
    },
    {
        "Date": "4/1/2019",
        "Open": "26075.10",
        "High": "26695.96",
        "Low": "26062.59",
        "Close": "26592.91"
    },
    {
        "Date": "3/1/2019",
        "Open": "26019.67",
        "High": "26155.98",
        "Low": "25208.00",
        "Close": "25928.68"
    },
    {
        "Date": "2/1/2019",
        "Open": "25025.31",
        "High": "26241.42",
        "Low": "24883.04",
        "Close": "25916.00"
    },
    {
        "Date": "1/1/2019",
        "Open": "23058.61",
        "High": "25109.62",
        "Low": "22638.41",
        "Close": "24999.67"
    },
    {
        "Date": "12/1/2018",
        "Open": "25779.57",
        "High": "25980.21",
        "Low": "21712.53",
        "Close": "23327.46"
    },
    {
        "Date": "11/1/2018",
        "Open": "25142.08",
        "High": "26277.82",
        "Low": "24268.74",
        "Close": "25538.46"
    },
    {
        "Date": "10/1/2018",
        "Open": "26598.36",
        "High": "26951.81",
        "Low": "24122.23",
        "Close": "25115.76"
    },
    {
        "Date": "9/1/2018",
        "Open": "25916.07",
        "High": "26769.16",
        "Low": "25754.32",
        "Close": "26458.31"
    },
    {
        "Date": "8/1/2018",
        "Open": "25461.63",
        "High": "26167.94",
        "Low": "24965.77",
        "Close": "25964.82"
    },
    {
        "Date": "7/1/2018",
        "Open": "24161.53",
        "High": "25587.24",
        "Low": "24077.56",
        "Close": "25415.19"
    },
    {
        "Date": "6/1/2018",
        "Open": "24542.09",
        "High": "25402.83",
        "Low": "23997.21",
        "Close": "24271.41"
    },
    {
        "Date": "5/1/2018",
        "Open": "24117.29",
        "High": "25086.49",
        "Low": "23531.31",
        "Close": "24415.84"
    },
    {
        "Date": "4/1/2018",
        "Open": "24076.60",
        "High": "24858.97",
        "Low": "23344.52",
        "Close": "24163.15"
    },
    {
        "Date": "3/1/2018",
        "Open": "25024.04",
        "High": "25449.15",
        "Low": "23509.06",
        "Close": "24103.11"
    },
    {
        "Date": "2/1/2018",
        "Open": "26083.04",
        "High": "26306.70",
        "Low": "23360.29",
        "Close": "25029.20"
    },
    {
        "Date": "1/1/2018",
        "Open": "24809.35",
        "High": "26616.71",
        "Low": "24741.70",
        "Close": "26149.39"
    },
    {
        "Date": "12/1/2017",
        "Open": "24305.40",
        "High": "24876.07",
        "Low": "23921.90",
        "Close": "24719.22"
    },
    {
        "Date": "11/1/2017",
        "Open": "23442.90",
        "High": "24327.82",
        "Low": "23242.75",
        "Close": "24272.35"
    },
    {
        "Date": "10/1/2017",
        "Open": "22423.47",
        "High": "23485.25",
        "Low": "22416.00",
        "Close": "23377.24"
    },
    {
        "Date": "9/1/2017",
        "Open": "21981.77",
        "High": "22419.51",
        "Low": "21709.63",
        "Close": "22405.09"
    },
    {
        "Date": "8/1/2017",
        "Open": "21961.42",
        "High": "22179.11",
        "Low": "21600.34",
        "Close": "21948.10"
    },
    {
        "Date": "7/1/2017",
        "Open": "21392.30",
        "High": "21929.80",
        "Low": "21279.30",
        "Close": "21891.12"
    },
    {
        "Date": "6/1/2017",
        "Open": "21030.55",
        "High": "21535.03",
        "Low": "20994.22",
        "Close": "21349.63"
    },
    {
        "Date": "5/1/2017",
        "Open": "20962.73",
        "High": "21112.32",
        "Low": "20553.45",
        "Close": "21008.65"
    },
    {
        "Date": "4/1/2017",
        "Open": "20665.17",
        "High": "21070.90",
        "Low": "20379.55",
        "Close": "20940.51"
    },
    {
        "Date": "3/1/2017",
        "Open": "20957.29",
        "High": "21169.11",
        "Low": "20412.80",
        "Close": "20663.22"
    },
    {
        "Date": "2/1/2017",
        "Open": "19923.81",
        "High": "20851.33",
        "Low": "19831.09",
        "Close": "20812.24"
    },
    {
        "Date": "1/1/2017",
        "Open": "19872.86",
        "High": "20125.58",
        "Low": "19677.94",
        "Close": "19864.09"
    }
]